directory_sso_api_client/__init__.py
directory_sso_api_client/backends.py
directory_sso_api_client/client.py
directory_sso_api_client/middleware.py
directory_sso_api_client/models.py
directory_sso_api_client/testapiclient.py
directory_sso_api_client/user.py
directory_sso_api_client-7.6.0.dist-info/licenses/LICENSE
directory_sso_api_client-7.6.0.dist-info/METADATA
directory_sso_api_client-7.6.0.dist-info/WHEEL
directory_sso_api_client-7.6.0.dist-info/top_level.txt
directory_sso_api_client-7.6.0.dist-info/RECORD
