Metadata-Version: 2.4
Name: directory_sso_api_client
Version: 7.6.0
Summary: Python API client for Export Directory.
Home-page: https://github.com/uktrade/directory-sso-api-client
Author: Department for Business and Trade
License: MIT
Classifier: Development Status :: 5 - Production/Stable
Classifier: Environment :: Web Environment
Classifier: Framework :: Django
Classifier: Framework :: Django :: 2.2
Classifier: Framework :: Django :: 3.2
Classifier: Framework :: Django :: 4.2
Classifier: Intended Audience :: Developers
Classifier: License :: OSI Approved :: MIT License
Classifier: Natural Language :: English
Classifier: Operating System :: OS Independent
Classifier: Programming Language :: Python :: 3.9
Classifier: Programming Language :: Python :: 3.13
Classifier: Topic :: Software Development :: Libraries :: Python Modules
License-File: LICENSE
Requires-Dist: directory_client_core<=8.0.0,>=7.3.1
Requires-Dist: tenacity==9.1.2
Provides-Extra: test
Requires-Dist: django<5.0,>=4.2.10; extra == "test"
Requires-Dist: black==23.1.0; extra == "test"
Requires-Dist: flake8; extra == "test"
Requires-Dist: isort==5.6.4; extra == "test"
Requires-Dist: pytest-cov; extra == "test"
Requires-Dist: pytest-django<4.11.1,>=3.8.0; extra == "test"
Requires-Dist: pytest-sugar<1.0.0,>=0.9.2; extra == "test"
Requires-Dist: pytest==8.4.2; extra == "test"
Requires-Dist: pytest-codecov; extra == "test"
Requires-Dist: GitPython; extra == "test"
Requires-Dist: requests<3.0.0,>=2.22.0; extra == "test"
Requires-Dist: requests_mock==1.7.0; extra == "test"
Requires-Dist: setuptools; extra == "test"
Requires-Dist: twine; extra == "test"
Requires-Dist: wheel<1.0.0,>=0.34.2; extra == "test"
Dynamic: author
Dynamic: classifier
Dynamic: description
Dynamic: description-content-type
Dynamic: home-page
Dynamic: license
Dynamic: license-file
Dynamic: provides-extra
Dynamic: requires-dist
Dynamic: summary
